simanneal/__init__.py
simanneal/anneal.py
simanneal-0.4.2.dist-info/METADATA
simanneal-0.4.2.dist-info/RECORD
simanneal-0.4.2.dist-info/WHEEL
simanneal-0.4.2.dist-info/top_level.txt
