Metadata-Version: 2.1
Name: simanneal
Version: 0.4.2
Summary: Simulated Annealing in Python
Home-page: https://github.com/perrygeo/simanneal
Author: Matthew Perry
Author-email: perrygeo@gmail.com
License: BSD
Platform: UNKNOWN
